{"commit_hash": "20972db5601fb45f8d7f5eb73e933bfdcb915caf", "env_name": "conda-py3.12-arb-automake-benchmark==1.5.0-boost-cpp-ccache-cppyythonizations-cxx-compiler-flatsurf__cppasv-fmt-gmp-gmpxxll-gmpxxyy-libeantic-libexactreal_=3.0.1-libintervalxt_=3.0.0-libtool-make-pyexactreal_=3.0.1-setuptools", "date": 1719961775000, "params": {"arch": "x86_64", "cpu": "Standard_DS2_v2", "machine": "Azure", "os": "Linux", "ram": "61830880", "python": "3.12", "arb": "", "automake": "", "benchmark==1.5.0": "", "boost-cpp": "", "ccache": "", "flatsurf::cppasv": "", "cppyythonizations": "", "cxx-compiler": "", "libeantic": "", "fmt": "", "gmp": "", "gmpxxll": "", "gmpxxyy": "", "libexactreal>=3.0.1": "", "libintervalxt>=3.0.0": "", "libtool": "", "make": "", "pyexactreal>=3.0.1": "", "setuptools": ""}, "python": "3.12", "requirements": {"arb": "", "automake": "", "benchmark==1.5.0": "", "boost-cpp": "", "ccache": "", "flatsurf::cppasv": "", "cppyythonizations": "", "cxx-compiler": "", "libeantic": "", "fmt": "", "gmp": "", "gmpxxll": "", "gmpxxyy": "", "libexactreal>=3.0.1": "", "libintervalxt>=3.0.0": "", "libtool": "", "make": "", "pyexactreal>=3.0.1": "", "setuptools": ""}, "env_vars": {}, "result_columns": ["result", "params", "version", "started_at", "duration", "stats_ci_99_a", "stats_ci_99_b", "stats_q_25", "stats_q_75", "stats_number", "stats_repeat", "samples", "profile"], "results": {"CopyAssignChain\u27e8long long\u27e9.track_time": [[224.25746323770238], [], "0", 1719962831238, 1.0195], "CopyConstructChain\u27e8long long\u27e9.track_time": [[223.58118769198464], [], "0", 1719962832258, 0.98334], "CreateChain\u27e8long long\u27e9.track_time": [[115.60982543428943], [], "0", 1719962833241, 0.88997], "FlatTriangulationCollapsedFlipCollapsed\u27e8Vector\u27e8eantic\u2237renf_elem_class\u27e9\u27e9.track_time": [[27417.916251005645], [], "0", 1719962834131, 1.7624], "FlatTriangulationCollapsedFlipCollapsed\u27e8Vector\u27e8exactreal\u2237Element\u27e8exactreal\u2237IntegerRing\u27e9\u27e9\u27e9.track_time": [[68104.1287642783], [], "0", 1719962835894, 1.7271], "FlatTriangulationCollapsedFlipCollapsed\u27e8Vector\u27e8long long\u27e9\u27e9.track_time": [[10108.802981912473], [], "0", 1719962837621, 1.1542], "FlatTriangulationCollapsedFlipCollapsed\u27e8Vector\u27e8mpq_class\u27e9\u27e9.track_time": [[22035.479481795217], [], "0", 1719962838775, 1.3323], "FlatTriangulationCollapsedFlipUncollapsed\u27e8Vector\u27e8eantic\u2237renf_elem_class\u27e9\u27e9.track_time": [[26376.97901302513], [], "0", 1719962840108, 1.0733], "FlatTriangulationCollapsedFlipUncollapsed\u27e8Vector\u27e8exactreal\u2237Element\u27e8exactreal\u2237IntegerRing\u27e9\u27e9\u27e9.track_time": [[61436.514497170225], [], "0", 1719962841181, 0.86018], "FlatTriangulationCollapsedFlipUncollapsed\u27e8Vector\u27e8long long\u27e9\u27e9.track_time": [[8845.62577177124], [], "0", 1719962842041, 0.8336], "FlatTriangulationCollapsedFlipUncollapsed\u27e8Vector\u27e8mpq_class\u27e9\u27e9.track_time": [[19383.802757975285], [], "0", 1719962842875, 0.97453], "FlatTriangulationCombinatorialFlip.track_time": [[1027.0679995604235], [], "0", 1719962843850, 0.88164], "FlatTriangulationEquality\u27e8Vector\u27e8eantic\u2237renf_elem_class\u27e9\u27e9.track_time": [[2136.8122228919906], [], "0", 1719962844731, 1.0175], "FlatTriangulationEquality\u27e8Vector\u27e8exactreal\u2237Element\u27e8exactreal\u2237IntegerRing\u27e9\u27e9\u27e9.track_time": [[4200.581323164242], [], "0", 1719962845749, 1.2313], "FlatTriangulationEquality\u27e8Vector\u27e8long long\u27e9\u27e9.track_time": [[184.6592893239325], [], "0", 1719962846980, 1.0048], "FlatTriangulationEquality\u27e8Vector\u27e8mpq_class\u27e9\u27e9.track_time": [[2690.3094623830075], [], "0", 1719962847985, 1.0801], "FlatTriangulationFlip\u27e8Vector\u27e8eantic\u2237renf_elem_class\u27e9\u27e9.track_time": [[6905.333596533653], [], "0", 1719962849066, 0.84516], "FlatTriangulationFlip\u27e8Vector\u27e8exactreal\u2237Element\u27e8exactreal\u2237IntegerRing\u27e9\u27e9\u27e9.track_time": [[25405.097687212714], [], "0", 1719962849911, 1.0184], "FlatTriangulationFlip\u27e8Vector\u27e8long long\u27e9\u27e9.track_time": [[2623.780981213113], [], "0", 1719962850929, 1.0675], "FlatTriangulationFlip\u27e8Vector\u27e8mpq_class\u27e9\u27e9.track_time": [[5318.058757614067], [], "0", 1719962851997, 0.82526], "FlatTriangulationTrivialEquality\u27e8Vector\u27e8eantic\u2237renf_elem_class\u27e9\u27e9.track_time": [[5.8770296177034895], [], "0", 1719962852822, 0.80813], "HalfEdgeIndex.track_time": [[2.4750652637601496, 2.6278273615334538], [["'-1'", "'1'"]], "0", 1719962853630, 2.026], "MoveChain\u27e8long long\u27e9.track_time": [[0.309625592835624], [], "0", 1719962855657, 1.0964], "PathConstructor\u27e8Vector\u27e8eantic\u2237renf_elem_class\u27e9\u27e9.track_time": [[908.4751223438425], [], "0", 1719962856753, 0.85833], "PathConstructor\u27e8Vector\u27e8long long\u27e9\u27e9.track_time": [[824.7390857915409], [], "0", 1719962857612, 0.88122], "SaddleConnectionUnaryMinus\u27e8Vector\u27e8eantic\u2237renf_elem_class\u27e9\u27e9.track_time": [[243.66054329237355], [], "0", 1719962858493, 1.095], "SaddleConnectionUnaryMinus\u27e8Vector\u27e8long long\u27e9\u27e9.track_time": [[252.02326648077639], [], "0", 1719962859588, 1.0805], "SaddleConnectionsByLength\u27e8Vector\u27e8eantic\u2237renf_elem_class\u27e9\u27e9.track_time": [[2581572.1780303037, 6385343578.000001], [["'1'", "'64'"]], "0", 1719962860669, 7.5207], "SaddleConnectionsByLength\u27e8Vector\u27e8exactreal\u2237Element\u27e8exactreal\u2237NumberField\u27e9\u27e9\u27e9.track_time": [[7901167.595505618, 12322428115.000002], [["'1'", "'64'"]], "0", 1719962868190, 13.247], "SaddleConnectionsLWithSlit\u27e8Vector\u27e8eantic\u2237renf_elem_class\u27e9\u27e9.track_time": [[391956.32414181205, 1112683.0158982514, 16048776.022727273], [["'1'", "'8'", "'64'"]], "0", 1719962881437, 3.0958], "SaddleConnectionsLWithSlit\u27e8Vector\u27e8mpq_class\u27e9\u27e9.track_time": [[388090.6902263943, 1263760.1135135137, 19578930.75], [["'1'", "'8'", "'64'"]], "0", 1719962884533, 3.1634], "SaddleConnectionsL\u27e8Vector\u27e8eantic\u2237renf_elem_class\u27e9\u27e9.track_time": [[422716.1165458938, 8011984.977011494, 1176984468.0], [["'1'", "'8'", "'64'"]], "0", 1719962887697, 3.2871], "SaddleConnectionsL\u27e8Vector\u27e8exactreal\u2237Element\u27e8exactreal\u2237IntegerRing\u27e9\u27e9\u27e9.track_time": [[1216579.4283216784, 18152560.769230768, 1859125202.0000002], [["'1'", "'8'", "'64'"]], "0", 1719962890984, 3.8301], "SaddleConnectionsL\u27e8Vector\u27e8long long\u27e9\u27e9.track_time": [[172982.2493218249, 4453186.835443038, 948341642.0], [["'1'", "'8'", "'64'"]], "0", 1719962894814, 3.2066], "SaddleConnectionsL\u27e8Vector\u27e8mpq_class\u27e9\u27e9.track_time": [[428682.2461913467, 9492546.14864865, 1326674375.0], [["'1'", "'8'", "'64'"]], "0", 1719962898021, 3.5768], "SaddleConnectionsSampleSquare\u27e8Vector\u27e8eantic\u2237renf_elem_class\u27e9\u27e9.track_time": [[769794.5956521739, 241295021.66666663], [["'256'", "'65536'"]], "0", 1719962901598, 2.4572], "SaddleConnectionsSampleSquare\u27e8Vector\u27e8exactreal\u2237Element\u27e8exactreal\u2237IntegerRing\u27e9\u27e9\u27e9.track_time": [[1539436.5774336283, 524127046.00000006], [["'256'", "'65536'"]], "0", 1719962904056, 1.4997], "SaddleConnectionsSampleSquare\u27e8Vector\u27e8long long\u27e9\u27e9.track_time": [[578591.8832781457, 192599033.33333334], [["'256'", "'65536'"]], "0", 1719962905556, 1.6685], "SaddleConnectionsSampleSquare\u27e8Vector\u27e8mpq_class\u27e9\u27e9.track_time": [[836195.8550724639, 272287978.00000006], [["'256'", "'65536'"]], "0", 1719962907225, 1.8217], "SaddleConnectionsSquare\u27e8Vector\u27e8eantic\u2237renf_elem_class\u27e9\u27e9.track_time": [[140863.05875323643, 2092620.041791045, 351601832.5], [["'1'", "'8'", "'64'"]], "0", 1719962909047, 3.0755], "SaddleConnectionsSquare\u27e8Vector\u27e8exactreal\u2237Element\u27e8exactreal\u2237IntegerRing\u27e9\u27e9\u27e9.track_time": [[392981.8862745097, 5379464.992187501, 563436171.0000001], [["'1'", "'8'", "'64'"]], "0", 1719962912122, 2.5623], "SaddleConnectionsSquare\u27e8Vector\u27e8long long\u27e9\u27e9.track_time": [[53772.70978120979, 1212061.1756521738, 290381532.50000006], [["'1'", "'8'", "'64'"]], "0", 1719962914685, 2.6903], "SaddleConnectionsSquare\u27e8Vector\u27e8mpq_class\u27e9\u27e9.track_time": [[148212.50191082802, 2254949.9904153356, 370559564.49999994], [["'1'", "'8'", "'64'"]], "0", 1719962917375, 3.1655], "VectorArb\u27e8eantic\u2237renf_elem_class\u27e9.track_time": [[575.8408928488863], [], "0", 1719962920541, 0.81192], "VectorArb\u27e8exactreal\u2237Element\u27e8exactreal\u2237IntegerRing\u27e9\u27e9.track_time": [[498.9637053804533], [], "0", 1719962921353, 1.297], "VectorArb\u27e8exactreal\u2237Element\u27e8exactreal\u2237NumberField\u27e9\u27e9.track_time": [[3634.300706399675], [], "0", 1719962922650, 1.1347], "VectorArb\u27e8exactreal\u2237Element\u27e8exactreal\u2237RationalField\u27e9\u27e9.track_time": [[553.4630523189435], [], "0", 1719962923785, 0.8039], "VectorArb\u27e8long long\u27e9.track_time": [[77.36013778338395], [], "0", 1719962924589, 0.81876], "VectorArb\u27e8mpq_class\u27e9.track_time": [[132.6638007002845], [], "0", 1719962925408, 0.89573], "VectorArb\u27e8mpz_class\u27e9.track_time": [[84.23329743204889], [], "0", 1719962926304, 0.87749], "VectorCcw\u27e8eantic\u2237renf_elem_class\u27e9.track_time": [[1298.5308537960584], [], "0", 1719962927181, 0.90797], "VectorCcw\u27e8exactreal\u2237Element\u27e8exactreal\u2237IntegerRing\u27e9\u27e9.track_time": [[1133.929901420315], [], "0", 1719962928089, 0.91291], "VectorCcw\u27e8exactreal\u2237Element\u27e8exactreal\u2237NumberField\u27e9\u27e9.track_time": [[7724.145584567506], [], "0", 1719962929002, 0.82819], "VectorCcw\u27e8exactreal\u2237Element\u27e8exactreal\u2237RationalField\u27e9\u27e9.track_time": [[1265.3366706006718], [], "0", 1719962929831, 0.88946], "VectorCcw\u27e8long long\u27e9.track_time": [[2.4749962449646117], [], "0", 1719962930720, 1.0024], "VectorCcw\u27e8mpq_class\u27e9.track_time": [[330.5363059195491], [], "0", 1719962931723, 1.1387], "VectorCcw\u27e8mpz_class\u27e9.track_time": [[106.05082956591275], [], "0", 1719962932862, 0.85923], "VectorDivInt\u27e8eantic\u2237renf_elem_class\u27e9.track_time": [[288.60473476361364], [], "0", 1719962933721, 1.0822], "VectorDivInt\u27e8exactreal\u2237Element\u27e8exactreal\u2237NumberField\u27e9\u27e9.track_time": [[509.6397877153978], [], "0", 1719962934803, 0.81226], "VectorDivInt\u27e8exactreal\u2237Element\u27e8exactreal\u2237RationalField\u27e9\u27e9.track_time": [[327.99236622161726], [], "0", 1719962935616, 1.1022], "VectorDivInt\u27e8long long\u27e9.track_time": [[18.098264315217953], [], "0", 1719962936718, 0.97801], "VectorDivInt\u27e8mpq_class\u27e9.track_time": [[254.90727327527983], [], "0", 1719962937696, 1.0289], "VectorDivInt\u27e8mpz_class\u27e9.track_time": [[70.5709725349999], [], "0", 1719962938725, 0.85062], "VectorDivMpz\u27e8eantic\u2237renf_elem_class\u27e9.track_time": [[261.0586419346646], [], "0", 1719962939576, 1.0507], "VectorDivMpz\u27e8exactreal\u2237Element\u27e8exactreal\u2237NumberField\u27e9\u27e9.track_time": [[458.3101388394074], [], "0", 1719962940626, 1.2896], "VectorDivMpz\u27e8exactreal\u2237Element\u27e8exactreal\u2237RationalField\u27e9\u27e9.track_time": [[381.57000986636353], [], "0", 1719962941916, 1.1909], "VectorDivMpz\u27e8long long\u27e9.track_time": [[66.98811025546954], [], "0", 1719962943107, 0.83516], "VectorDivMpz\u27e8mpq_class\u27e9.track_time": [[311.5034663573127], [], "0", 1719962943942, 1.1348], "VectorDivMpz\u27e8mpz_class\u27e9.track_time": [[82.99446354453512], [], "0", 1719962945077, 0.83482], "VectorEqVector\u27e8eantic\u2237renf_elem_class\u27e9.track_time": [[124.5108169314236], [], "0", 1719962945912, 0.87593], "VectorEqVector\u27e8exactreal\u2237Element\u27e8exactreal\u2237IntegerRing\u27e9\u27e9.track_time": [[206.0488059673869], [], "0", 1719962946788, 1.0174], "VectorEqVector\u27e8exactreal\u2237Element\u27e8exactreal\u2237NumberField\u27e9\u27e9.track_time": [[400.0013705482136], [], "0", 1719962947806, 1.2425], "VectorEqVector\u27e8exactreal\u2237Element\u27e8exactreal\u2237RationalField\u27e9\u27e9.track_time": [[280.3649053197179], [], "0", 1719962949048, 1.0612], "VectorEqVector\u27e8long long\u27e9.track_time": [[2.781990375822536], [], "0", 1719962950110, 1.0992], "VectorEqVector\u27e8mpq_class\u27e9.track_time": [[130.3915064928808], [], "0", 1719962951209, 0.90053], "VectorEqVector\u27e8mpz_class\u27e9.track_time": [[65.4530271760858], [], "0", 1719962952109, 0.84115], "VectorLtBound\u27e8eantic\u2237renf_elem_class\u27e9.track_time": [[1133.5835267011182], [], "0", 1719962952951, 0.90946], "VectorLtBound\u27e8exactreal\u2237Element\u27e8exactreal\u2237IntegerRing\u27e9\u27e9.track_time": [[976.5754501096774], [], "0", 1719962953860, 0.88367], "VectorLtBound\u27e8exactreal\u2237Element\u27e8exactreal\u2237NumberField\u27e9\u27e9.track_time": [[4290.894685804154], [], "0", 1719962954744, 1.2605], "VectorLtBound\u27e8exactreal\u2237Element\u27e8exactreal\u2237RationalField\u27e9\u27e9.track_time": [[1052.086664130438], [], "0", 1719962956005, 0.86057], "VectorLtBound\u27e8long long\u27e9.track_time": [[69.33442282167182], [], "0", 1719962956865, 0.81595], "VectorLtBound\u27e8mpq_class\u27e9.track_time": [[450.73886969032804], [], "0", 1719962957681, 1.2714], "VectorLtBound\u27e8mpz_class\u27e9.track_time": [[169.72474776091457], [], "0", 1719962958953, 0.92606], "VectorMinus\u27e8eantic\u2237renf_elem_class\u27e9.track_time": [[288.10780686278986], [], "0", 1719962959879, 1.0855], "VectorMinus\u27e8exactreal\u2237Element\u27e8exactreal\u2237IntegerRing\u27e9\u27e9.track_time": [[335.21496118567114], [], "0", 1719962960965, 1.1063], "VectorMinus\u27e8exactreal\u2237Element\u27e8exactreal\u2237NumberField\u27e9\u27e9.track_time": [[905.3066533260092], [], "0", 1719962962071, 0.83839], "VectorMinus\u27e8exactreal\u2237Element\u27e8exactreal\u2237RationalField\u27e9\u27e9.track_time": [[533.3363179849616], [], "0", 1719962962909, 0.81512], "VectorMinus\u27e8long long\u27e9.track_time": [[31.994353388787136], [], "0", 1719962963725, 1.1276], "VectorMinus\u27e8mpq_class\u27e9.track_time": [[318.8151621492182], [], "0", 1719962964852, 1.1111], "VectorMinus\u27e8mpz_class\u27e9.track_time": [[134.35527260279997], [], "0", 1719962965963, 0.89432], "VectorOrientation\u27e8eantic\u2237renf_elem_class\u27e9.track_time": [[1392.3348253843374], [], "0", 1719962966858, 0.88783], "VectorOrientation\u27e8exactreal\u2237Element\u27e8exactreal\u2237IntegerRing\u27e9\u27e9.track_time": [[1205.934404751809], [], "0", 1719962967746, 0.87438], "VectorOrientation\u27e8exactreal\u2237Element\u27e8exactreal\u2237NumberField\u27e9\u27e9.track_time": [[7592.40149709318], [], "0", 1719962968620, 0.84111], "VectorOrientation\u27e8exactreal\u2237Element\u27e8exactreal\u2237RationalField\u27e9\u27e9.track_time": [[1326.231933091847], [], "0", 1719962969461, 0.9195], "VectorOrientation\u27e8long long\u27e9.track_time": [[2.4753923780763594], [], "0", 1719962970381, 1.0581], "VectorOrientation\u27e8mpq_class\u27e9.track_time": [[154.1580894240452], [], "0", 1719962971439, 0.94882], "VectorOrientation\u27e8mpz_class\u27e9.track_time": [[51.051601884490786], [], "0", 1719962972388, 0.83268], "VectorPerpendicular\u27e8eantic\u2237renf_elem_class\u27e9.track_time": [[103.30444538140141], [], "0", 1719962973221, 0.86888], "VectorPerpendicular\u27e8exactreal\u2237Element\u27e8exactreal\u2237IntegerRing\u27e9\u27e9.track_time": [[185.8818536590017], [], "0", 1719962974090, 0.98904], "VectorPerpendicular\u27e8exactreal\u2237Element\u27e8exactreal\u2237NumberField\u27e9\u27e9.track_time": [[500.828197259179], [], "0", 1719962975079, 0.83846], "VectorPerpendicular\u27e8exactreal\u2237Element\u27e8exactreal\u2237RationalField\u27e9\u27e9.track_time": [[243.3938014088337], [], "0", 1719962975918, 1.0151], "VectorPerpendicular\u27e8long long\u27e9.track_time": [[16.10651918163456], [], "0", 1719962976933, 0.94498], "VectorPerpendicular\u27e8mpq_class\u27e9.track_time": [[102.53182815114602], [], "0", 1719962977878, 0.90366], "VectorPerpendicular\u27e8mpz_class\u27e9.track_time": [[61.29767484221121], [], "0", 1719962978782, 0.81691], "VectorPlus\u27e8eantic\u2237renf_elem_class\u27e9.track_time": [[232.24006425239455], [], "0", 1719962979599, 0.99634], "VectorPlus\u27e8exactreal\u2237Element\u27e8exactreal\u2237IntegerRing\u27e9\u27e9.track_time": [[159.5170970670949], [], "0", 1719962980595, 0.93803], "VectorPlus\u27e8exactreal\u2237Element\u27e8exactreal\u2237NumberField\u27e9\u27e9.track_time": [[407.15480449435046], [], "0", 1719962981533, 1.1989], "VectorPlus\u27e8exactreal\u2237Element\u27e8exactreal\u2237RationalField\u27e9\u27e9.track_time": [[281.9135256040116], [], "0", 1719962982732, 1.0767], "VectorPlus\u27e8long long\u27e9.track_time": [[19.23106750215377], [], "0", 1719962983809, 0.9751], "VectorPlus\u27e8mpq_class\u27e9.track_time": [[208.572388116815], [], "0", 1719962984784, 0.99784], "VectorPlus\u27e8mpz_class\u27e9.track_time": [[82.37995548832386], [], "0", 1719962985782, 0.84816], "VectorTimesInt\u27e8eantic\u2237renf_elem_class\u27e9.track_time": [[195.7227341511317], [], "0", 1719962986630, 0.97789], "VectorTimesInt\u27e8exactreal\u2237Element\u27e8exactreal\u2237IntegerRing\u27e9\u27e9.track_time": [[150.2428712382832], [], "0", 1719962987608, 0.91414], "VectorTimesInt\u27e8exactreal\u2237Element\u27e8exactreal\u2237NumberField\u27e9\u27e9.track_time": [[352.57191348847874], [], "0", 1719962988523, 1.1301], "VectorTimesInt\u27e8exactreal\u2237Element\u27e8exactreal\u2237RationalField\u27e9\u27e9.track_time": [[325.31881796051096], [], "0", 1719962989653, 1.1014], "VectorTimesInt\u27e8long long\u27e9.track_time": [[18.33177460986728], [], "0", 1719962990754, 0.96349], "VectorTimesInt\u27e8mpq_class\u27e9.track_time": [[252.4903478648056], [], "0", 1719962991718, 1.0416], "VectorTimesInt\u27e8mpz_class\u27e9.track_time": [[81.47003762256041], [], "0", 1719962992760, 0.8467], "VectorTimesMpz\u27e8eantic\u2237renf_elem_class\u27e9.track_time": [[193.88235010220228], [], "0", 1719962993606, 0.94207], "VectorTimesMpz\u27e8exactreal\u2237Element\u27e8exactreal\u2237IntegerRing\u27e9\u27e9.track_time": [[155.38739287939342], [], "0", 1719962994549, 0.93878], "VectorTimesMpz\u27e8exactreal\u2237Element\u27e8exactreal\u2237NumberField\u27e9\u27e9.track_time": [[391.50143986726624], [], "0", 1719962995487, 1.2068], "VectorTimesMpz\u27e8exactreal\u2237Element\u27e8exactreal\u2237RationalField\u27e9\u27e9.track_time": [[383.43073380194403], [], "0", 1719962996694, 1.1658], "VectorTimesMpz\u27e8long long\u27e9.track_time": [[53.71526038937607], [], "0", 1719962997860, 0.79973], "VectorTimesMpz\u27e8mpq_class\u27e9.track_time": [[312.6624772949996], [], "0", 1719962998660, 1.0812], "VectorTimesMpz\u27e8mpz_class\u27e9.track_time": [[83.24099163955526], [], "0", 1719962999741, 0.8624], "VectorTimesVector\u27e8eantic\u2237renf_elem_class\u27e9.track_time": [[347.4613618798463], [], "0", 1719963000604, 1.151], "VectorTimesVector\u27e8exactreal\u2237Element\u27e8exactreal\u2237IntegerRing\u27e9\u27e9.track_time": [[813.0360762087579], [], "0", 1719963001755, 0.86479], "VectorTimesVector\u27e8exactreal\u2237Element\u27e8exactreal\u2237NumberField\u27e9\u27e9.track_time": [[3961.6600117738967], [], "0", 1719963002620, 1.2049], "VectorTimesVector\u27e8exactreal\u2237Element\u27e8exactreal\u2237RationalField\u27e9\u27e9.track_time": [[1321.231882971867], [], "0", 1719963003825, 0.92399], "VectorTimesVector\u27e8long long\u27e9.track_time": [[2.7959684457524636], [], "0", 1719963004749, 1.1017], "VectorTimesVector\u27e8mpq_class\u27e9.track_time": [[152.8439760446024], [], "0", 1719963005851, 0.90275], "VectorTimesVector\u27e8mpz_class\u27e9.track_time": [[50.651523538176086], [], "0", 1719963006754, 0.84027], "VectorUnaryMinus\u27e8eantic\u2237renf_elem_class\u27e9.track_time": [[93.57030406322909], [], "0", 1719963007594, 0.88997], "VectorUnaryMinus\u27e8exactreal\u2237Element\u27e8exactreal\u2237IntegerRing\u27e9\u27e9.track_time": [[171.22100702735048], [], "0", 1719963008484, 0.96962], "VectorUnaryMinus\u27e8exactreal\u2237Element\u27e8exactreal\u2237NumberField\u27e9\u27e9.track_time": [[516.7744473902458], [], "0", 1719963009454, 0.81795], "VectorUnaryMinus\u27e8exactreal\u2237Element\u27e8exactreal\u2237RationalField\u27e9\u27e9.track_time": [[227.3486280686226], [], "0", 1719963010272, 0.99828], "VectorUnaryMinus\u27e8long long\u27e9.track_time": [[16.21910696754319], [], "0", 1719963011270, 0.92936], "VectorUnaryMinus\u27e8mpq_class\u27e9.track_time": [[99.99264611651303], [], "0", 1719963012200, 0.86869], "VectorUnaryMinus\u27e8mpz_class\u27e9.track_time": [[56.0520237075738], [], "0", 1719963013068, 0.79285], "VertexAtSource.track_time": [[14.01321755231522], [], "0", 1719963013861, 0.89124], "VertexAtTarget.track_time": [[17.963905912234363], [], "0", 1719963014753, 0.94723]}, "durations": {}, "version": 2}