{
    "benchmark_version": {
        "binary.BinarySuite.time_1_1_2_2": "8008e6ad29b00736db27b3ef39983fa4a2a557b84d001bb4dc9956b1ce73e6a7",
        "binary.BinarySuite.time_1_1_3_5": "8008e6ad29b00736db27b3ef39983fa4a2a557b84d001bb4dc9956b1ce73e6a7",
        "binary.BinarySuite.time_1_1_4_6": "8008e6ad29b00736db27b3ef39983fa4a2a557b84d001bb4dc9956b1ce73e6a7",
        "binary.BinarySuite.time_1_2_1_2": "8008e6ad29b00736db27b3ef39983fa4a2a557b84d001bb4dc9956b1ce73e6a7",
        "binary.BinarySuite.time_1_2_2_3": "8008e6ad29b00736db27b3ef39983fa4a2a557b84d001bb4dc9956b1ce73e6a7",
        "binary.BinarySuite.time_1_2_2_5": "8008e6ad29b00736db27b3ef39983fa4a2a557b84d001bb4dc9956b1ce73e6a7",
        "binary.BinarySuite.time_1_3_2_2": "8008e6ad29b00736db27b3ef39983fa4a2a557b84d001bb4dc9956b1ce73e6a7",
        "binary.BinarySuite.time_1_4_3_4": "8008e6ad29b00736db27b3ef39983fa4a2a557b84d001bb4dc9956b1ce73e6a7",
        "binary.BinarySuite.time_1_5_1_3": "8008e6ad29b00736db27b3ef39983fa4a2a557b84d001bb4dc9956b1ce73e6a7",
        "binary.BinarySuite.time_1_5_2_2": "8008e6ad29b00736db27b3ef39983fa4a2a557b84d001bb4dc9956b1ce73e6a7",
        "binary.BinarySuite.time_1_5_2_4": "8008e6ad29b00736db27b3ef39983fa4a2a557b84d001bb4dc9956b1ce73e6a7",
        "binary.BinarySuite.time_1_6_1_4": "8008e6ad29b00736db27b3ef39983fa4a2a557b84d001bb4dc9956b1ce73e6a7",
        "binary.BinarySuite.time_1_8_3_6": "8008e6ad29b00736db27b3ef39983fa4a2a557b84d001bb4dc9956b1ce73e6a7",
        "binary.BinarySuite.time_1_8_3_8": "8008e6ad29b00736db27b3ef39983fa4a2a557b84d001bb4dc9956b1ce73e6a7",
        "binary.BinarySuite.time_1_8_5_6": "8008e6ad29b00736db27b3ef39983fa4a2a557b84d001bb4dc9956b1ce73e6a7",
        "binary.BinarySuite.time_2_2_4_4": "8008e6ad29b00736db27b3ef39983fa4a2a557b84d001bb4dc9956b1ce73e6a7",
        "binary.BinarySuite.time_2_2_6_10": "8008e6ad29b00736db27b3ef39983fa4a2a557b84d001bb4dc9956b1ce73e6a7",
        "binary.BinarySuite.time_2_4_2_4": "8008e6ad29b00736db27b3ef39983fa4a2a557b84d001bb4dc9956b1ce73e6a7",
        "binary.BinarySuite.time_2_4_3_3": "8008e6ad29b00736db27b3ef39983fa4a2a557b84d001bb4dc9956b1ce73e6a7",
        "binary.BinarySuite.time_2_7_3_6": "8008e6ad29b00736db27b3ef39983fa4a2a557b84d001bb4dc9956b1ce73e6a7",
        "binary.BinarySuite.time_2_7_5_6": "8008e6ad29b00736db27b3ef39983fa4a2a557b84d001bb4dc9956b1ce73e6a7",
        "binary.BinarySuite.time_2_8_6_8": "8008e6ad29b00736db27b3ef39983fa4a2a557b84d001bb4dc9956b1ce73e6a7",
        "binary.BinarySuite.time_3_6_3_6": "8008e6ad29b00736db27b3ef39983fa4a2a557b84d001bb4dc9956b1ce73e6a7",
        "binary.BinarySuite.time_3_6_5_6": "8008e6ad29b00736db27b3ef39983fa4a2a557b84d001bb4dc9956b1ce73e6a7",
        "binary.BinarySuite.time_3_7_4_6": "8008e6ad29b00736db27b3ef39983fa4a2a557b84d001bb4dc9956b1ce73e6a7"
    },
    "commit_hash": "bb1b951d0339008acbc0074a5bfefec349ce0eb0",
    "date": 1548642885000,
    "ended_at": {
        "binary.BinarySuite.time_1_1_2_2": 1548803162208,
        "binary.BinarySuite.time_1_1_3_5": 1548803166322,
        "binary.BinarySuite.time_1_1_4_6": 1548803171736,
        "binary.BinarySuite.time_1_2_1_2": 1548803176047,
        "binary.BinarySuite.time_1_2_2_3": 1548803180960,
        "binary.BinarySuite.time_1_2_2_5": 1548803187929,
        "binary.BinarySuite.time_1_3_2_2": 1548803193042,
        "binary.BinarySuite.time_1_4_3_4": 1548803195350,
        "binary.BinarySuite.time_1_5_1_3": 1548803199465,
        "binary.BinarySuite.time_1_5_2_2": 1548803205983,
        "binary.BinarySuite.time_1_5_2_4": 1548803211046,
        "binary.BinarySuite.time_1_6_1_4": 1548803212302,
        "binary.BinarySuite.time_1_8_3_6": 1548803222176,
        "binary.BinarySuite.time_1_8_3_8": 1548803233706,
        "binary.BinarySuite.time_1_8_5_6": 1548803244884,
        "binary.BinarySuite.time_2_2_4_4": 1548803251602,
        "binary.BinarySuite.time_2_2_6_10": 1548803263379,
        "binary.BinarySuite.time_2_4_2_4": 1548803268993,
        "binary.BinarySuite.time_2_4_3_3": 1548803275560,
        "binary.BinarySuite.time_2_7_3_6": 1548803286092,
        "binary.BinarySuite.time_2_7_5_6": 1548803298168,
        "binary.BinarySuite.time_2_8_6_8": 1548803304634,
        "binary.BinarySuite.time_3_6_3_6": 1548803312404,
        "binary.BinarySuite.time_3_6_5_6": 1548803322832,
        "binary.BinarySuite.time_3_7_4_6": 1548803334258
    },
    "env_name": "conda-py3.6-plumbum",
    "params": {
        "machine": "circleci",
        "plumbum": "",
        "python": "3.6"
    },
    "profiles": {},
    "python": "3.6",
    "requirements": {
        "plumbum": ""
    },
    "results": {
        "binary.BinarySuite.time_1_1_2_2": {
            "result": [
                0.8484168025000258
            ],
            "stats": [
                {
                    "ci_99": [
                        0.8388931289999846,
                        0.8610889819999556
                    ],
                    "max": 0.8610889819999556,
                    "mean": 0.8480741116999866,
                    "min": 0.8388931289999846,
                    "number": 1,
                    "q_25": 0.8433952450000106,
                    "q_75": 0.8503455592499733,
                    "repeat": 10,
                    "std": 0.006355035741980863
                }
            ]
        },
        "binary.BinarySuite.time_1_1_3_5": {
            "result": [
                0.6768811919999962
            ],
            "stats": [
                {
                    "ci_99": [
                        0.6588679959999126,
                        0.6866952300000548
                    ],
                    "max": 0.6866952300000548,
                    "mean": 0.675507202599988,
                    "min": 0.6588679959999126,
                    "number": 1,
                    "q_25": 0.6727917274999697,
                    "q_75": 0.678612918749991,
                    "repeat": 10,
                    "std": 0.007871026016776977
                }
            ]
        },
        "binary.BinarySuite.time_1_1_4_6": {
            "result": [
                0.8866604519999441
            ],
            "stats": [
                {
                    "ci_99": [
                        0.8767936760000339,
                        0.8948062859999482
                    ],
                    "max": 0.8948062859999482,
                    "mean": 0.8861783284000012,
                    "min": 0.8767936760000339,
                    "number": 1,
                    "q_25": 0.8816913965000026,
                    "q_75": 0.889135211000081,
                    "repeat": 10,
                    "std": 0.005413990154721346
                }
            ]
        },
        "binary.BinarySuite.time_1_2_1_2": {
            "result": [
                0.7039006044999496
            ],
            "stats": [
                {
                    "ci_99": [
                        0.6839951559999236,
                        0.7187744960000373
                    ],
                    "max": 0.7187744960000373,
                    "mean": 0.7036648842999966,
                    "min": 0.6839951559999236,
                    "number": 1,
                    "q_25": 0.6983618207500228,
                    "q_75": 0.7078168012500612,
                    "repeat": 10,
                    "std": 0.00939814789265349
                }
            ]
        },
        "binary.BinarySuite.time_1_2_2_3": {
            "result": [
                0.7993293879999896
            ],
            "stats": [
                {
                    "ci_99": [
                        0.785381245999929,
                        0.8490120590000743
                    ],
                    "max": 0.8490120590000743,
                    "mean": 0.8015106476000028,
                    "min": 0.785381245999929,
                    "number": 1,
                    "q_25": 0.7911201117499616,
                    "q_75": 0.8025484620000043,
                    "repeat": 10,
                    "std": 0.017162843749446603
                }
            ]
        },
        "binary.BinarySuite.time_1_2_2_5": {
            "result": [
                1.1480858670000202
            ],
            "stats": [
                {
                    "ci_99": [
                        1.1337002249999841,
                        1.1886406339999667
                    ],
                    "max": 1.1886406339999667,
                    "mean": 1.152983848700012,
                    "min": 1.1337002249999841,
                    "number": 1,
                    "q_25": 1.142972521750039,
                    "q_75": 1.1591571115000079,
                    "repeat": 10,
                    "std": 0.01586999769208948
                }
            ]
        },
        "binary.BinarySuite.time_1_3_2_2": {
            "result": [
                0.841990489000068
            ],
            "stats": [
                {
                    "ci_99": [
                        0.827088142999969,
                        0.8805989869999848
                    ],
                    "max": 0.8805989869999848,
                    "mean": 0.8440529302000073,
                    "min": 0.827088142999969,
                    "number": 1,
                    "q_25": 0.8360323842499326,
                    "q_75": 0.8480264570000315,
                    "repeat": 10,
                    "std": 0.01435010765462567
                }
            ]
        },
        "binary.BinarySuite.time_1_4_3_4": {
            "result": [
                0.37587264350003124
            ],
            "stats": [
                {
                    "ci_99": [
                        0.3643054649999158,
                        0.38500356999998075
                    ],
                    "max": 0.38500356999998075,
                    "mean": 0.37510830989999705,
                    "min": 0.3643054649999158,
                    "number": 1,
                    "q_25": 0.37134354125001323,
                    "q_75": 0.3775945092500024,
                    "repeat": 10,
                    "std": 0.0059079070338368305
                }
            ]
        },
        "binary.BinarySuite.time_1_5_1_3": {
            "result": [
                0.6747208019999675
            ],
            "stats": [
                {
                    "ci_99": [
                        0.6644476469999745,
                        0.6893219410000029
                    ],
                    "max": 0.6893219410000029,
                    "mean": 0.6763323997000044,
                    "min": 0.6644476469999745,
                    "number": 1,
                    "q_25": 0.6722520287499663,
                    "q_75": 0.6808032092500866,
                    "repeat": 10,
                    "std": 0.006713053623192374
                }
            ]
        },
        "binary.BinarySuite.time_1_5_2_2": {
            "result": [
                1.0727634275000355
            ],
            "stats": [
                {
                    "ci_99": [
                        1.0618883600000117,
                        1.0786941830000387
                    ],
                    "max": 1.0786941830000387,
                    "mean": 1.0729106716999923,
                    "min": 1.0618883600000117,
                    "number": 1,
                    "q_25": 1.0711282442499908,
                    "q_75": 1.0767869597499384,
                    "repeat": 10,
                    "std": 0.004641790018819259
                }
            ]
        },
        "binary.BinarySuite.time_1_5_2_4": {
            "result": [
                0.8230581619999384
            ],
            "stats": [
                {
                    "ci_99": [
                        0.8153779439999198,
                        0.8321586589999015
                    ],
                    "max": 0.8321586589999015,
                    "mean": 0.8241217356999755,
                    "min": 0.8153779439999198,
                    "number": 1,
                    "q_25": 0.8210070015000213,
                    "q_75": 0.8275713869999777,
                    "repeat": 10,
                    "std": 0.00520865648245289
                }
            ]
        },
        "binary.BinarySuite.time_1_6_1_4": {
            "result": [
                0.19296818749995737
            ],
            "stats": [
                {
                    "ci_99": [
                        0.1893973809999352,
                        0.1943563570000606
                    ],
                    "max": 0.1943563570000606,
                    "mean": 0.19266122749999112,
                    "min": 0.1893973809999352,
                    "number": 1,
                    "q_25": 0.19268335175001994,
                    "q_75": 0.1939943737499732,
                    "repeat": 10,
                    "std": 0.0016830096227387482
                }
            ]
        },
        "binary.BinarySuite.time_1_8_3_6": {
            "result": [
                1.6336907589999896
            ],
            "stats": [
                {
                    "ci_99": [
                        1.6052297370000588,
                        1.6473390930000278
                    ],
                    "max": 1.6473390930000278,
                    "mean": 1.6307223352000164,
                    "min": 1.6052297370000588,
                    "number": 1,
                    "q_25": 1.6238581794999902,
                    "q_75": 1.63749204100003,
                    "repeat": 10,
                    "std": 0.011822779806219862
                }
            ]
        },
        "binary.BinarySuite.time_1_8_3_8": {
            "result": [
                2.873560502000032
            ],
            "stats": [
                {
                    "ci_99": [
                        2.815002626000023,
                        2.9008106011665116
                    ],
                    "max": 2.881453224999973,
                    "mean": 2.858064173666681,
                    "min": 2.815002626000023,
                    "number": 1,
                    "q_25": 2.836731643500002,
                    "q_75": 2.8786547477500335,
                    "repeat": 6,
                    "std": 0.027094669081403285
                }
            ]
        },
        "binary.BinarySuite.time_1_8_5_6": {
            "result": [
                2.7230468705000703
            ],
            "stats": [
                {
                    "ci_99": [
                        2.6845764044940967,
                        2.798947207000083
                    ],
                    "max": 2.798947207000083,
                    "mean": 2.7413474806666613,
                    "min": 2.7088672029999543,
                    "number": 1,
                    "q_25": 2.7136034849999646,
                    "q_75": 2.768552499999913,
                    "repeat": 6,
                    "std": 0.03545837586971247
                }
            ]
        },
        "binary.BinarySuite.time_2_2_4_4": {
            "result": [
                1.0988173280000524
            ],
            "stats": [
                {
                    "ci_99": [
                        1.0799162239999305,
                        1.1121111759998712
                    ],
                    "max": 1.1121111759998712,
                    "mean": 1.0980128329999843,
                    "min": 1.0799162239999305,
                    "number": 1,
                    "q_25": 1.0922708062500135,
                    "q_75": 1.103254985499916,
                    "repeat": 10,
                    "std": 0.009095009554983297
                }
            ]
        },
        "binary.BinarySuite.time_2_2_6_10": {
            "result": [
                1.9410433944999
            ],
            "stats": [
                {
                    "ci_99": [
                        1.9163843290000386,
                        1.9709888400000182
                    ],
                    "max": 1.9709888400000182,
                    "mean": 1.9407764093000082,
                    "min": 1.9163843290000386,
                    "number": 1,
                    "q_25": 1.931352930499969,
                    "q_75": 1.9472129970001788,
                    "repeat": 10,
                    "std": 0.0142659309105776
                }
            ]
        },
        "binary.BinarySuite.time_2_4_2_4": {
            "result": [
                0.916335914000058
            ],
            "stats": [
                {
                    "ci_99": [
                        0.9024488340000971,
                        0.9241796520000207
                    ],
                    "max": 0.9241796520000207,
                    "mean": 0.9145730759000343,
                    "min": 0.9024488340000971,
                    "number": 1,
                    "q_25": 0.9081755472499538,
                    "q_75": 0.9207699582499913,
                    "repeat": 10,
                    "std": 0.007606836518930149
                }
            ]
        },
        "binary.BinarySuite.time_2_4_3_3": {
            "result": [
                1.0748142534999374
            ],
            "stats": [
                {
                    "ci_99": [
                        1.062104344999966,
                        1.1032606759999908
                    ],
                    "max": 1.1032606759999908,
                    "mean": 1.076249613499988,
                    "min": 1.062104344999966,
                    "number": 1,
                    "q_25": 1.0662992947499959,
                    "q_75": 1.0831804795000437,
                    "repeat": 10,
                    "std": 0.012025920942540536
                }
            ]
        },
        "binary.BinarySuite.time_2_7_3_6": {
            "result": [
                1.721620651999956
            ],
            "stats": [
                {
                    "ci_99": [
                        1.6977719520000392,
                        1.7493288360001316
                    ],
                    "max": 1.7493288360001316,
                    "mean": 1.7233146640999621,
                    "min": 1.6977719520000392,
                    "number": 1,
                    "q_25": 1.703938136749997,
                    "q_75": 1.7424713269999188,
                    "repeat": 10,
                    "std": 0.019917543116617458
                }
            ]
        },
        "binary.BinarySuite.time_2_7_5_6": {
            "result": [
                2.3797940985000423
            ],
            "stats": [
                {
                    "ci_99": [
                        2.361864824999998,
                        2.4368032919999223
                    ],
                    "max": 2.4368032919999223,
                    "mean": 2.393927554000001,
                    "min": 2.361864824999998,
                    "number": 1,
                    "q_25": 2.370366175250041,
                    "q_75": 2.4262541992499393,
                    "repeat": 8,
                    "std": 0.02975531178726756
                }
            ]
        },
        "binary.BinarySuite.time_2_8_6_8": {
            "result": [
                1.0572253905000366
            ],
            "stats": [
                {
                    "ci_99": [
                        1.0479432939999924,
                        1.0829469499999504
                    ],
                    "max": 1.0829469499999504,
                    "mean": 1.0594849178000119,
                    "min": 1.0479432939999924,
                    "number": 1,
                    "q_25": 1.0517545957499408,
                    "q_75": 1.0640455792500063,
                    "repeat": 10,
                    "std": 0.010293085275233666
                }
            ]
        },
        "binary.BinarySuite.time_3_6_3_6": {
            "result": [
                1.280101372000047
            ],
            "stats": [
                {
                    "ci_99": [
                        1.2631294919999618,
                        1.290760384000123
                    ],
                    "max": 1.290760384000123,
                    "mean": 1.2782618258000185,
                    "min": 1.2631294919999618,
                    "number": 1,
                    "q_25": 1.271468579499981,
                    "q_75": 1.2844012772500264,
                    "repeat": 10,
                    "std": 0.009085403608778535
                }
            ]
        },
        "binary.BinarySuite.time_3_6_5_6": {
            "result": [
                2.584532901999978
            ],
            "stats": [
                {
                    "ci_99": [
                        2.5607940403929144,
                        2.6290180890000556
                    ],
                    "max": 2.6290180890000556,
                    "mean": 2.5906613670000334,
                    "min": 2.569194325000012,
                    "number": 1,
                    "q_25": 2.5774113700001067,
                    "q_75": 2.597372569000015,
                    "repeat": 6,
                    "std": 0.01982172063172608
                }
            ]
        },
        "binary.BinarySuite.time_3_7_4_6": {
            "result": [
                2.2616029354999228
            ],
            "stats": [
                {
                    "ci_99": [
                        2.236915096000075,
                        2.316850865000106
                    ],
                    "max": 2.316850865000106,
                    "mean": 2.267532709125021,
                    "min": 2.236915096000075,
                    "number": 1,
                    "q_25": 2.249523091250097,
                    "q_75": 2.2759643794999818,
                    "repeat": 8,
                    "std": 0.025984682426513847
                }
            ]
        }
    },
    "started_at": {
        "binary.BinarySuite.time_1_1_2_2": 1548803157043,
        "binary.BinarySuite.time_1_1_3_5": 1548803162209,
        "binary.BinarySuite.time_1_1_4_6": 1548803166323,
        "binary.BinarySuite.time_1_2_1_2": 1548803171736,
        "binary.BinarySuite.time_1_2_2_3": 1548803176048,
        "binary.BinarySuite.time_1_2_2_5": 1548803180961,
        "binary.BinarySuite.time_1_3_2_2": 1548803187929,
        "binary.BinarySuite.time_1_4_3_4": 1548803193042,
        "binary.BinarySuite.time_1_5_1_3": 1548803195350,
        "binary.BinarySuite.time_1_5_2_2": 1548803199465,
        "binary.BinarySuite.time_1_5_2_4": 1548803205983,
        "binary.BinarySuite.time_1_6_1_4": 1548803211047,
        "binary.BinarySuite.time_1_8_3_6": 1548803212302,
        "binary.BinarySuite.time_1_8_3_8": 1548803222176,
        "binary.BinarySuite.time_1_8_5_6": 1548803233706,
        "binary.BinarySuite.time_2_2_4_4": 1548803244884,
        "binary.BinarySuite.time_2_2_6_10": 1548803251602,
        "binary.BinarySuite.time_2_4_2_4": 1548803263379,
        "binary.BinarySuite.time_2_4_3_3": 1548803268993,
        "binary.BinarySuite.time_2_7_3_6": 1548803275560,
        "binary.BinarySuite.time_2_7_5_6": 1548803286092,
        "binary.BinarySuite.time_2_8_6_8": 1548803298169,
        "binary.BinarySuite.time_3_6_3_6": 1548803304634,
        "binary.BinarySuite.time_3_6_5_6": 1548803312405,
        "binary.BinarySuite.time_3_7_4_6": 1548803322832
    },
    "version": 1
}