{
    "benchmark_version": {
        "binary.BinarySuite.time_1_1_2_2": "8008e6ad29b00736db27b3ef39983fa4a2a557b84d001bb4dc9956b1ce73e6a7",
        "binary.BinarySuite.time_1_1_3_5": "8008e6ad29b00736db27b3ef39983fa4a2a557b84d001bb4dc9956b1ce73e6a7",
        "binary.BinarySuite.time_1_1_4_6": "8008e6ad29b00736db27b3ef39983fa4a2a557b84d001bb4dc9956b1ce73e6a7",
        "binary.BinarySuite.time_1_2_1_2": "8008e6ad29b00736db27b3ef39983fa4a2a557b84d001bb4dc9956b1ce73e6a7",
        "binary.BinarySuite.time_1_2_2_3": "8008e6ad29b00736db27b3ef39983fa4a2a557b84d001bb4dc9956b1ce73e6a7",
        "binary.BinarySuite.time_1_2_2_5": "8008e6ad29b00736db27b3ef39983fa4a2a557b84d001bb4dc9956b1ce73e6a7",
        "binary.BinarySuite.time_1_3_2_2": "8008e6ad29b00736db27b3ef39983fa4a2a557b84d001bb4dc9956b1ce73e6a7",
        "binary.BinarySuite.time_1_4_3_4": "8008e6ad29b00736db27b3ef39983fa4a2a557b84d001bb4dc9956b1ce73e6a7",
        "binary.BinarySuite.time_1_5_1_3": "8008e6ad29b00736db27b3ef39983fa4a2a557b84d001bb4dc9956b1ce73e6a7",
        "binary.BinarySuite.time_1_5_2_2": "8008e6ad29b00736db27b3ef39983fa4a2a557b84d001bb4dc9956b1ce73e6a7",
        "binary.BinarySuite.time_1_5_2_4": "8008e6ad29b00736db27b3ef39983fa4a2a557b84d001bb4dc9956b1ce73e6a7",
        "binary.BinarySuite.time_1_6_1_4": "8008e6ad29b00736db27b3ef39983fa4a2a557b84d001bb4dc9956b1ce73e6a7",
        "binary.BinarySuite.time_1_8_3_6": "8008e6ad29b00736db27b3ef39983fa4a2a557b84d001bb4dc9956b1ce73e6a7",
        "binary.BinarySuite.time_1_8_3_8": "8008e6ad29b00736db27b3ef39983fa4a2a557b84d001bb4dc9956b1ce73e6a7",
        "binary.BinarySuite.time_1_8_5_6": "8008e6ad29b00736db27b3ef39983fa4a2a557b84d001bb4dc9956b1ce73e6a7",
        "binary.BinarySuite.time_2_2_4_4": "8008e6ad29b00736db27b3ef39983fa4a2a557b84d001bb4dc9956b1ce73e6a7",
        "binary.BinarySuite.time_2_2_6_10": "8008e6ad29b00736db27b3ef39983fa4a2a557b84d001bb4dc9956b1ce73e6a7",
        "binary.BinarySuite.time_2_4_2_4": "8008e6ad29b00736db27b3ef39983fa4a2a557b84d001bb4dc9956b1ce73e6a7",
        "binary.BinarySuite.time_2_4_3_3": "8008e6ad29b00736db27b3ef39983fa4a2a557b84d001bb4dc9956b1ce73e6a7",
        "binary.BinarySuite.time_2_7_3_6": "8008e6ad29b00736db27b3ef39983fa4a2a557b84d001bb4dc9956b1ce73e6a7",
        "binary.BinarySuite.time_2_7_5_6": "8008e6ad29b00736db27b3ef39983fa4a2a557b84d001bb4dc9956b1ce73e6a7",
        "binary.BinarySuite.time_2_8_6_8": "8008e6ad29b00736db27b3ef39983fa4a2a557b84d001bb4dc9956b1ce73e6a7",
        "binary.BinarySuite.time_3_6_3_6": "8008e6ad29b00736db27b3ef39983fa4a2a557b84d001bb4dc9956b1ce73e6a7",
        "binary.BinarySuite.time_3_6_5_6": "8008e6ad29b00736db27b3ef39983fa4a2a557b84d001bb4dc9956b1ce73e6a7",
        "binary.BinarySuite.time_3_7_4_6": "8008e6ad29b00736db27b3ef39983fa4a2a557b84d001bb4dc9956b1ce73e6a7"
    },
    "commit_hash": "bb1b951d0339008acbc0074a5bfefec349ce0eb0",
    "date": 1548642885000,
    "ended_at": {
        "binary.BinarySuite.time_1_1_2_2": 1548805764684,
        "binary.BinarySuite.time_1_1_3_5": 1548805768798,
        "binary.BinarySuite.time_1_1_4_6": 1548805774165,
        "binary.BinarySuite.time_1_2_1_2": 1548805778478,
        "binary.BinarySuite.time_1_2_2_3": 1548805783295,
        "binary.BinarySuite.time_1_2_2_5": 1548805790169,
        "binary.BinarySuite.time_1_3_2_2": 1548805795186,
        "binary.BinarySuite.time_1_4_3_4": 1548805797444,
        "binary.BinarySuite.time_1_5_1_3": 1548805801558,
        "binary.BinarySuite.time_1_5_2_2": 1548805807984,
        "binary.BinarySuite.time_1_5_2_4": 1548805812899,
        "binary.BinarySuite.time_1_6_1_4": 1548805814109,
        "binary.BinarySuite.time_1_8_3_6": 1548805823692,
        "binary.BinarySuite.time_1_8_3_8": 1548805834574,
        "binary.BinarySuite.time_1_8_5_6": 1548805845156,
        "binary.BinarySuite.time_2_2_4_4": 1548805852032,
        "binary.BinarySuite.time_2_2_6_10": 1548805863114,
        "binary.BinarySuite.time_2_4_2_4": 1548805868484,
        "binary.BinarySuite.time_2_4_3_3": 1548805874803,
        "binary.BinarySuite.time_2_7_3_6": 1548805884733,
        "binary.BinarySuite.time_2_7_5_6": 1548805896016,
        "binary.BinarySuite.time_2_8_6_8": 1548805902085,
        "binary.BinarySuite.time_3_6_3_6": 1548805909509,
        "binary.BinarySuite.time_3_6_5_6": 1548805921843,
        "binary.BinarySuite.time_3_7_4_6": 1548805932572
    },
    "env_name": "conda-py3.6-plumbum",
    "params": {
        "machine": "circleci",
        "plumbum": "",
        "python": "3.6"
    },
    "profiles": {},
    "python": "3.6",
    "requirements": {
        "plumbum": ""
    },
    "results": {
        "binary.BinarySuite.time_1_1_2_2": {
            "result": [
                0.8356749440000044
            ],
            "stats": [
                {
                    "ci_99": [
                        0.8297507529999848,
                        0.8539249969999219
                    ],
                    "max": 0.8539249969999219,
                    "mean": 0.8385769160999871,
                    "min": 0.8297507529999848,
                    "number": 1,
                    "q_25": 0.8343786412500549,
                    "q_75": 0.8430864709999639,
                    "repeat": 10,
                    "std": 0.007285220714916782
                }
            ]
        },
        "binary.BinarySuite.time_1_1_3_5": {
            "result": [
                0.6643975934999844
            ],
            "stats": [
                {
                    "ci_99": [
                        0.6472859919999792,
                        0.6782704390000163
                    ],
                    "max": 0.6782704390000163,
                    "mean": 0.6641685600999949,
                    "min": 0.6472859919999792,
                    "number": 1,
                    "q_25": 0.6597353549999525,
                    "q_75": 0.6685809457499943,
                    "repeat": 10,
                    "std": 0.007998860365722772
                }
            ]
        },
        "binary.BinarySuite.time_1_1_4_6": {
            "result": [
                0.87169114149998
            ],
            "stats": [
                {
                    "ci_99": [
                        0.8568722909999451,
                        0.9158871140000429
                    ],
                    "max": 0.9158871140000429,
                    "mean": 0.8763550446999829,
                    "min": 0.8568722909999451,
                    "number": 1,
                    "q_25": 0.8647399997500145,
                    "q_75": 0.8845076902499613,
                    "repeat": 10,
                    "std": 0.016305592442185296
                }
            ]
        },
        "binary.BinarySuite.time_1_2_1_2": {
            "result": [
                0.7026450815000658
            ],
            "stats": [
                {
                    "ci_99": [
                        0.6888995319999367,
                        0.715058231999933
                    ],
                    "max": 0.715058231999933,
                    "mean": 0.7017333488999953,
                    "min": 0.6888995319999367,
                    "number": 1,
                    "q_25": 0.6986605469999461,
                    "q_75": 0.7039732692499854,
                    "repeat": 10,
                    "std": 0.007140623464113816
                }
            ]
        },
        "binary.BinarySuite.time_1_2_2_3": {
            "result": [
                0.786719990999984
            ],
            "stats": [
                {
                    "ci_99": [
                        0.7742297720000124,
                        0.8046398459999864
                    ],
                    "max": 0.8046398459999864,
                    "mean": 0.7881489042999874,
                    "min": 0.7742297720000124,
                    "number": 1,
                    "q_25": 0.781935461249958,
                    "q_75": 0.7950539265000032,
                    "repeat": 10,
                    "std": 0.009363701444421729
                }
            ]
        },
        "binary.BinarySuite.time_1_2_2_5": {
            "result": [
                1.1258251029999542
            ],
            "stats": [
                {
                    "ci_99": [
                        1.1083921919999966,
                        1.4664205590000847
                    ],
                    "max": 1.4664205590000847,
                    "mean": 1.1612056634000054,
                    "min": 1.1083921919999966,
                    "number": 1,
                    "q_25": 1.1180282962499746,
                    "q_75": 1.1403945032500076,
                    "repeat": 10,
                    "std": 0.10275803525959469
                }
            ]
        },
        "binary.BinarySuite.time_1_3_2_2": {
            "result": [
                0.8236700030000179
            ],
            "stats": [
                {
                    "ci_99": [
                        0.8073010950000707,
                        0.8336671199999728
                    ],
                    "max": 0.8336671199999728,
                    "mean": 0.8209165831000291,
                    "min": 0.8073010950000707,
                    "number": 1,
                    "q_25": 0.8141329880000399,
                    "q_75": 0.8276819830000761,
                    "repeat": 10,
                    "std": 0.009065038482024796
                }
            ]
        },
        "binary.BinarySuite.time_1_4_3_4": {
            "result": [
                0.36071431900001016
            ],
            "stats": [
                {
                    "ci_99": [
                        0.3534702209999523,
                        0.3706756949999317
                    ],
                    "max": 0.3706756949999317,
                    "mean": 0.3617936411000187,
                    "min": 0.3534702209999523,
                    "number": 1,
                    "q_25": 0.3560154220000413,
                    "q_75": 0.36854399225006773,
                    "repeat": 10,
                    "std": 0.0065079347291183845
                }
            ]
        },
        "binary.BinarySuite.time_1_5_1_3": {
            "result": [
                0.656955890499944
            ],
            "stats": [
                {
                    "ci_99": [
                        0.6442388549999123,
                        0.6781294039999466
                    ],
                    "max": 0.6781294039999466,
                    "mean": 0.6587023372999739,
                    "min": 0.6442388549999123,
                    "number": 1,
                    "q_25": 0.6548961419999841,
                    "q_75": 0.6623333567499685,
                    "repeat": 10,
                    "std": 0.008396993581692443
                }
            ]
        },
        "binary.BinarySuite.time_1_5_2_2": {
            "result": [
                1.046067490500036
            ],
            "stats": [
                {
                    "ci_99": [
                        1.0368572480000466,
                        1.0668181759999698
                    ],
                    "max": 1.0668181759999698,
                    "mean": 1.049948732400003,
                    "min": 1.0368572480000466,
                    "number": 1,
                    "q_25": 1.0432187380000641,
                    "q_75": 1.0547300029999462,
                    "repeat": 10,
                    "std": 0.009861891227956563
                }
            ]
        },
        "binary.BinarySuite.time_1_5_2_4": {
            "result": [
                0.800315160499963
            ],
            "stats": [
                {
                    "ci_99": [
                        0.7876313420000542,
                        0.8263911569999891
                    ],
                    "max": 0.8263911569999891,
                    "mean": 0.8012324951999859,
                    "min": 0.7876313420000542,
                    "number": 1,
                    "q_25": 0.791669108749943,
                    "q_75": 0.8049488110000027,
                    "repeat": 10,
                    "std": 0.011292483058531233
                }
            ]
        },
        "binary.BinarySuite.time_1_6_1_4": {
            "result": [
                0.18657114149999643
            ],
            "stats": [
                {
                    "ci_99": [
                        0.18226233200005026,
                        0.1958980279999878
                    ],
                    "max": 0.1958980279999878,
                    "mean": 0.18749905400001127,
                    "min": 0.18226233200005026,
                    "number": 1,
                    "q_25": 0.1832839697499935,
                    "q_75": 0.19097954699998354,
                    "repeat": 10,
                    "std": 0.004564547929640649
                }
            ]
        },
        "binary.BinarySuite.time_1_8_3_6": {
            "result": [
                1.5723382149999452
            ],
            "stats": [
                {
                    "ci_99": [
                        1.558622569000022,
                        1.5926442040000666
                    ],
                    "max": 1.5926442040000666,
                    "mean": 1.5715215903000057,
                    "min": 1.558622569000022,
                    "number": 1,
                    "q_25": 1.5621843084999796,
                    "q_75": 1.5771511070000486,
                    "repeat": 10,
                    "std": 0.01049282836386691
                }
            ]
        },
        "binary.BinarySuite.time_1_8_3_8": {
            "result": [
                2.6924692124999865
            ],
            "stats": [
                {
                    "ci_99": [
                        2.6765015089999906,
                        2.702679888794373
                    ],
                    "max": 2.7005690419999837,
                    "mean": 2.6909791916666563,
                    "min": 2.6765015089999906,
                    "number": 1,
                    "q_25": 2.6883975124999893,
                    "q_75": 2.695736724249997,
                    "repeat": 6,
                    "std": 0.007649803829387991
                }
            ]
        },
        "binary.BinarySuite.time_1_8_5_6": {
            "result": [
                2.5872922419999895
            ],
            "stats": [
                {
                    "ci_99": [
                        2.5408887486771885,
                        2.721964466000145
                    ],
                    "max": 2.721964466000145,
                    "mean": 2.610326107666689,
                    "min": 2.5634326669999155,
                    "number": 1,
                    "q_25": 2.5841708980000817,
                    "q_75": 2.610956494749985,
                    "repeat": 6,
                    "std": 0.0524371789865999
                }
            ]
        },
        "binary.BinarySuite.time_2_2_4_4": {
            "result": [
                1.0936904739999704
            ],
            "stats": [
                {
                    "ci_99": [
                        1.060392042999979,
                        1.1345867759998782
                    ],
                    "max": 1.1345867759998782,
                    "mean": 1.0960772361999944,
                    "min": 1.060392042999979,
                    "number": 1,
                    "q_25": 1.0679309525000065,
                    "q_75": 1.1251579142499395,
                    "repeat": 10,
                    "std": 0.029883810601622693
                }
            ]
        },
        "binary.BinarySuite.time_2_2_6_10": {
            "result": [
                1.8348301340000717
            ],
            "stats": [
                {
                    "ci_99": [
                        1.8242773829999805,
                        1.851610255999958
                    ],
                    "max": 1.851610255999958,
                    "mean": 1.8348020669999983,
                    "min": 1.8242773829999805,
                    "number": 1,
                    "q_25": 1.8275686260000157,
                    "q_75": 1.8390018037499942,
                    "repeat": 10,
                    "std": 0.008114873933908041
                }
            ]
        },
        "binary.BinarySuite.time_2_4_2_4": {
            "result": [
                0.8852943279999863
            ],
            "stats": [
                {
                    "ci_99": [
                        0.87362948100008,
                        0.8952429570000504
                    ],
                    "max": 0.8952429570000504,
                    "mean": 0.8850064806999967,
                    "min": 0.87362948100008,
                    "number": 1,
                    "q_25": 0.8823918317499988,
                    "q_75": 0.8896808232499893,
                    "repeat": 10,
                    "std": 0.00696403115718387
                }
            ]
        },
        "binary.BinarySuite.time_2_4_3_3": {
            "result": [
                1.0416670270000168
            ],
            "stats": [
                {
                    "ci_99": [
                        1.0313341539999783,
                        1.0588978939999834
                    ],
                    "max": 1.0588978939999834,
                    "mean": 1.041647622100004,
                    "min": 1.0313341539999783,
                    "number": 1,
                    "q_25": 1.0360414477500228,
                    "q_75": 1.0456470374999753,
                    "repeat": 10,
                    "std": 0.007752104314876927
                }
            ]
        },
        "binary.BinarySuite.time_2_7_3_6": {
            "result": [
                1.650805250000019
            ],
            "stats": [
                {
                    "ci_99": [
                        1.6346749369999998,
                        1.6629388579999613
                    ],
                    "max": 1.6629388579999613,
                    "mean": 1.6499666183000046,
                    "min": 1.6346749369999998,
                    "number": 1,
                    "q_25": 1.6399294997500533,
                    "q_75": 1.6596921945000247,
                    "repeat": 10,
                    "std": 0.010577030503429567
                }
            ]
        },
        "binary.BinarySuite.time_2_7_5_6": {
            "result": [
                2.242057659000011
            ],
            "stats": [
                {
                    "ci_99": [
                        2.2271378580001056,
                        2.401304890000006
                    ],
                    "max": 2.401304890000006,
                    "mean": 2.2665142331250365,
                    "min": 2.2271378580001056,
                    "number": 1,
                    "q_25": 2.231160145250101,
                    "q_75": 2.2705267730000003,
                    "repeat": 8,
                    "std": 0.05519124210553901
                }
            ]
        },
        "binary.BinarySuite.time_2_8_6_8": {
            "result": [
                1.0001828895000813
            ],
            "stats": [
                {
                    "ci_99": [
                        0.9842074149999007,
                        1.0595193269999754
                    ],
                    "max": 1.0595193269999754,
                    "mean": 1.0036218482000208,
                    "min": 0.9842074149999007,
                    "number": 1,
                    "q_25": 0.989903129500135,
                    "q_75": 1.005973268999952,
                    "repeat": 10,
                    "std": 0.020574234178716795
                }
            ]
        },
        "binary.BinarySuite.time_3_6_3_6": {
            "result": [
                1.2220762584999534
            ],
            "stats": [
                {
                    "ci_99": [
                        1.2099589679999099,
                        1.2376119790000075
                    ],
                    "max": 1.2376119790000075,
                    "mean": 1.2225442285999861,
                    "min": 1.2099589679999099,
                    "number": 1,
                    "q_25": 1.2176501152500236,
                    "q_75": 1.2259339450000653,
                    "repeat": 10,
                    "std": 0.008307393757224306
                }
            ]
        },
        "binary.BinarySuite.time_3_6_5_6": {
            "result": [
                2.4600743185000056
            ],
            "stats": [
                {
                    "ci_99": [
                        2.442965390999916,
                        2.474917345999984
                    ],
                    "max": 2.474917345999984,
                    "mean": 2.4582440133750083,
                    "min": 2.442965390999916,
                    "number": 1,
                    "q_25": 2.448980841500088,
                    "q_75": 2.4647013452499777,
                    "repeat": 8,
                    "std": 0.011147897890898968
                }
            ]
        },
        "binary.BinarySuite.time_3_7_4_6": {
            "result": [
                2.1341431354999827
            ],
            "stats": [
                {
                    "ci_99": [
                        2.1154590450000796,
                        2.1455653120000306
                    ],
                    "max": 2.1455653120000306,
                    "mean": 2.1313162152499956,
                    "min": 2.1154590450000796,
                    "number": 1,
                    "q_25": 2.127752050999902,
                    "q_75": 2.1350064270000644,
                    "repeat": 8,
                    "std": 0.008716836390962364
                }
            ]
        }
    },
    "started_at": {
        "binary.BinarySuite.time_1_1_2_2": 1548805759567,
        "binary.BinarySuite.time_1_1_3_5": 1548805764684,
        "binary.BinarySuite.time_1_1_4_6": 1548805768798,
        "binary.BinarySuite.time_1_2_1_2": 1548805774165,
        "binary.BinarySuite.time_1_2_2_3": 1548805778479,
        "binary.BinarySuite.time_1_2_2_5": 1548805783296,
        "binary.BinarySuite.time_1_3_2_2": 1548805790170,
        "binary.BinarySuite.time_1_4_3_4": 1548805795186,
        "binary.BinarySuite.time_1_5_1_3": 1548805797445,
        "binary.BinarySuite.time_1_5_2_2": 1548805801559,
        "binary.BinarySuite.time_1_5_2_4": 1548805807984,
        "binary.BinarySuite.time_1_6_1_4": 1548805812900,
        "binary.BinarySuite.time_1_8_3_6": 1548805814110,
        "binary.BinarySuite.time_1_8_3_8": 1548805823692,
        "binary.BinarySuite.time_1_8_5_6": 1548805834574,
        "binary.BinarySuite.time_2_2_4_4": 1548805845157,
        "binary.BinarySuite.time_2_2_6_10": 1548805852033,
        "binary.BinarySuite.time_2_4_2_4": 1548805863114,
        "binary.BinarySuite.time_2_4_3_3": 1548805868484,
        "binary.BinarySuite.time_2_7_3_6": 1548805874803,
        "binary.BinarySuite.time_2_7_5_6": 1548805884733,
        "binary.BinarySuite.time_2_8_6_8": 1548805896017,
        "binary.BinarySuite.time_3_6_3_6": 1548805902085,
        "binary.BinarySuite.time_3_6_5_6": 1548805909509,
        "binary.BinarySuite.time_3_7_4_6": 1548805921843
    },
    "version": 1
}